ms_ovba_crypto.py
ms_ovba_crypto-1.0.0.dist-info/LICENSE
ms_ovba_crypto-1.0.0.dist-info/METADATA
ms_ovba_crypto-1.0.0.dist-info/WHEEL
ms_ovba_crypto-1.0.0.dist-info/top_level.txt
ms_ovba_crypto-1.0.0.dist-info/RECORD
