Metadata-Version: 2.1
Name: ms-ovba-crypto
Version: 1.0.0
Summary: Encryption and hashing functions for Office VBA files.
Author-email: Kevin Nowaczyk <beakerboy99@yahoo.com>
Project-URL: Homepage, https://github.com/Beakerboy/MS-OVBA-Crypto
Project-URL: Bug Tracker, https://github.com/Beakerboy/MS-OVBA-Crypto/issues
Classifier: Programming Language :: Python :: 3
Classifier: License :: OSI Approved :: MIT License
Classifier: Operating System :: OS Independent
Requires-Python: >=3.7
License-File: LICENSE
Provides-Extra: tests
Requires-Dist: coveralls ; extra == 'tests'
Requires-Dist: flake8-annotations ; extra == 'tests'
Requires-Dist: mypy ; extra == 'tests'
Requires-Dist: pytest ; extra == 'tests'
Requires-Dist: pytest-cov ; extra == 'tests'
Requires-Dist: pep8-naming ; extra == 'tests'
